[
  { "rule": "foo @=>bar", "summary": "2020-01-12T17:30:25", "enable": false },
  { "rule": "zh[oō]ngn[aá]nh[aǎ]i @=>中南海" },
  { "rule": "b[eě]i\\s*j[iīì]ng @=>北京" },
  { "rule": "b[iì]j[iì]ng @=>毕竟" },
  { "rule": "ch[eé]ng\\s*r[eé]n @=>成人" },
  { "rule": "ch[oō]ngd[oò]ng @=>冲动" },
  { "rule": "d[ìi]f[aā]ng @=>地方" },
  { "rule": "d[iì]\\s*d[uū] @=>帝都" },
  { "rule": "d[uú]\\s*c[aá]i @=>独裁" },
  { "rule": "d[uú]\\s*l[iì] @=>独立" },
  { "rule": "f[aǎ]ngfo @=>仿佛" },
  { "rule": "f[eè]nnu @=>愤怒" },
  { "rule": "g[aǎ]nji[aà]o @=>感觉" },
  { "rule": "guoch[eé]n @=>过程" },
  { "rule": "gu[aā]nx[iì] @=>关系" },
  { "rule": "h[aǎ]oxi[aà]ng @=>好像" },
  { "rule": "j[iī]li[eè] @=>激烈" },
  { "rule": "ji[eē]chu @=>接触" },
  { "rule": "j[uù]li[eè] @=>剧烈" },
  { "rule": "j[iī]ngy[aà]n @=>经验" },
  { "rule": "j[iì]ngh[aá]ng @=>进行" },
  { "rule": "j[iì]nh[aá]ng @=>进行" },
  { "rule": "j[iī]ngsh[eé]n @=>精神" },
  { "rule": "k[eě]n[eé]ng @=>可能" },
  { "rule": "m[aǎ]ny[iì] @=>满意" },
  { "rule": "m[aǎ]sh[aà]ng @=>马上" },
  { "rule": "m[eé]iy[ǒo]u @=>没有" },
  { "rule": "m[ií]nzh[uǔ] @=>民主" },
  { "rule": "m[ií]ngb[aá]i @=>明白" },
  { "rule": "n[eé]ngg[oò]u @=>能够" },
  { "rule": "nàme @=>那么" },
  { "rule": "p[aá]ngbi[aā]n @=>旁边" },
  { "rule": "q[ií]gu[aà]i @=>奇怪" },
  { "rule": "q[iī]ngch[uǔ] @=>清楚" },
  { "rule": "r[eé]n\\s*ji[aā]n @=>人间" },
  { "rule": "r[oó]ngy[iì] @=>容易" },
  { "rule": "r[uú]gu[oǒ] @=>如果" },
  { "rule": "sh[iì]ji[eè] @=>世界" },
  { "rule": "sh[ií]ji[aā]n @=>时间" },
  { "rule": "sh[ií]me @=>什么" },
  { "rule": "t[oō]nggu[oò] @=>通过" },
  { "rule": "t[uū]r[aá]n @=>突然" },
  { "rule": "w[eē]ixi[eé] @=>威胁" },
  { "rule": "w[eè]izh[iì] @=>位置" },
  { "rule": "x[iī]\\s*z[aà]ng @=>西藏" },
  { "rule": "y[iī]di[aǎ]n @=>一点" },
  { "rule": "y[iī]y[aà]ng @=>一样" },
  { "rule": "y[iī]t[iǐ] @=>一体" },
  { "rule": "y[iǐ]j[iī]ng @=>已经" },
  { "rule": "z[iì]j[iǐ] @=>自己" },
  { "rule": "z[iì]\\s*y[oó]u @=>自由" },
  { "rule": "zh[eè]ng\\s*f[uǔ] @=>政府" },
  { "rule": "zh[iī]dào @=>知道" },
  { "rule": "zh[oō]w[eé]i @=>周围" },
  { "rule": "zh[oō]ng\\s*y[aā]ng @=>中央" },
  { "rule": "chuáng @=>床" },
  { "rule": "chéng @=>成" },
  { "rule": "zhōng @=>中" },
  { "rule": "xiōng @=>胸" },
  { "rule": "jiāng @=>江" },
  { "rule": "bāng @=>棒" },
  { "rule": "cháo @=>潮" },
  { "rule": "chōu @=>抽" },
  { "rule": "chūn @=>春" },
  { "rule": "chún @=>唇" },
  { "rule": "dàng @=>荡" },
  { "rule": "dòng @=>洞" },
  { "rule": "jiāo @=>交" },
  { "rule": "jiān @=>奸" },
  { "rule": "jīng @=>精" },
  { "rule": "jǐng @=>警" },
  { "rule": "làng @=>浪" },
  { "rule": "luàn @=>乱" },
  { "rule": "méng @=>蒙" },
  { "rule": "niao @=>尿" },
  { "rule": "nòng @=>弄" },
  { "rule": "piáo @=>嫖" },
  { "rule": "shēn @=>呻" },
  { "rule": "tiān @=>舔" },
  { "rule": "tǐng @=>挺" },
  { "rule": "xiǎo @=>小" },
  { "rule": "xìng @=>性" },
  { "rule": "yāng @=>央" },
  { "rule": "báo @=>薄" },
  { "rule": "bào @=>爆" },
  { "rule": "běi @=>北" },
  { "rule": "c[āà]o @=>操" },
  { "rule": "cuō @=>搓" },
  { "rule": "chā @=>插" },
  { "rule": "féi @=>肥" },
  { "rule": "hòu @=>厚" },
  { "rule": "huā @=>花" },
  { "rule": "huò @=>惑" },
  { "rule": "jān @=>奸" },
  { "rule": "kào @=>靠" },
  { "rule": "hún @=>魂" },
  { "rule": "liú @=>流" },
  { "rule": "luǒ @=>裸" },
  { "rule": "máo @=>毛" },
  { "rule": "mèi @=>昧" },
  { "rule": "mén @=>门" },
  { "rule": "mín @=>民" },
  { "rule": "nǎi @=>奶" },
  { "rule": "nèn @=>嫩" },
  { "rule": "rén @=>人" },
  { "rule": "róu @=>揉" },
  { "rule": "ròu @=>肉" },
  { "rule": "sāo @=>骚" },
  { "rule": "shā @=>杀" },
  { "rule": "shè @=>射" },
  { "rule": "shì @=>侍" },
  { "rule": "tún @=>臀" },
  { "rule": "tuǐ @=>腿" },
  { "rule": "wěn @=>吻" },
  { "rule": "xùe @=>穴" },
  { "rule": "xué @=>穴" },
  { "rule": "yào @=>药" },
  { "rule": "yàn @=>艳" },
  { "rule": "yīn @=>阴" },
  { "rule": "yín @=>淫" },
  { "rule": "yòu @=>诱" },
  { "rule": "zhǔ @=>主" },
  { "rule": "bī @=>逼" },
  { "rule": "bō @=>波" },
  { "rule": "bó @=>薄" },
  { "rule": "cō @=>抽" },
  { "rule": "dà @=>大" },
  { "rule": "fǎ @=>法" },
  { "rule": "fǔ @=>府" },
  { "rule": "fù @=>妇" },
  { "rule": "jī @=>激" },
  { "rule": "jì @=>妓" },
  { "rule": "lù @=>露" },
  { "rule": "mí @=>迷" },
  { "rule": "mì @=>蜜" },
  { "rule": "mō @=>摸" },
  { "rule": "rì @=>日" },
  { "rule": "rǔ @=>乳" },
  { "rule": "sè @=>色" },
  { "rule": "sī @=>私" },
  { "rule": "sǐ @=>死" },
  { "rule": "xí @=>习" },
  { "rule": "yù @=>欲" },
  { "rule": "xiangdao @=>想到" },
  { "rule": "liliang @=>力量" },
  { "rule": "shengli @=>胜利" },
  { "rule": "danshi @=>但是" },
  { "rule": "shihou @=>时候" },
  { "rule": "xiwang @=>希望" },
  { "rule": "youhuo @=>诱惑" },
  { "rule": "zuo'ai @=>做爱" },
  { "rule": "zuoyou @=>左右" },
  { "rule": "shuji @=>书记" },
  { "rule": "yiyin @=>意淫" },
  { "rule": "bobo @=>波波" },
  { "rule": "momo @=>摸摸" },
  { "rule": "[^a-z]chuang[^a-z] @=>床" },
  { "rule": "[^a-z]xiong[^a-z] @=>胸" },
  { "rule": "[^a-z]bian[^a-z] @=>变" },
  { "rule": "[^a-z]chun[^a-z] @=>春" },
  { "rule": "[^a-z]dang[^a-z] @=>党" },
  { "rule": "[^a-z]diao[^a-z] @=>屌" },
  { "rule": "[^a-z]feng[^a-z] @=>风" },
  { "rule": "[^a-z]lang[^a-z] @=>浪" },
  { "rule": "[^a-z]jian[^a-z] @=>贱" },
  { "rule": "[^a-z]jing[^a-z] @=>精" },
  { "rule": "[^a-z]qing[^a-z] @=>情" },
  { "rule": "[^a-z]quan[^a-z] @=>全" },
  { "rule": "[^a-z]tian[^a-z] @=>舔" },
  { "rule": "[^a-z]ting[^a-z] @=>挺" },
  { "rule": "[^a-z]xing[^a-z] @=>性" },
  { "rule": "[^a-z]cao[^a-z] @=>操" },
  { "rule": "[^a-z]dan[^a-z] @=>蛋" },
  { "rule": "[^a-z]huo[^a-z] @=>惑" },
  { "rule": "[^a-z]hou[^a-z] @=>厚" },
  { "rule": "[^a-z]hun[^a-z] @=>魂" },
  { "rule": "[^a-z]jie[^a-z] @=>劫" },
  { "rule": "[^a-z]kao[^a-z] @=>靠" },
  { "rule": "[^a-z]liu[^a-z] @=>流" },
  { "rule": "[^a-z]lou[^a-z] @=>露" },
  { "rule": "[^a-z]luo[^a-z] @=>裸" },
  { "rule": "[^a-z]lun[^a-z] @=>伦" },
  { "rule": "[^a-z]mei[^a-z] @=>魅" },
  { "rule": "[^a-z]nan[^a-z] @=>男" },
  { "rule": "[^a-z]nei[^a-z] @=>内" },
  { "rule": "[^a-z]nnd[^a-z] @=>奶奶的" },
  { "rule": "[^a-z]ren[^a-z] @=>人" },
  { "rule": "[^a-z]sao[^a-z] @=>骚" },
  { "rule": "[^a-z]sha[^a-z] @=>杀" },
  { "rule": "[^a-z]she[^a-z] @=>射" },
  { "rule": "[^a-z]shi[^a-z] @=>屎" },
  { "rule": "[^a-z]tai[^a-z] @=>态" },
  { "rule": "[^a-z]tui[^a-z] @=>腿" },
  { "rule": "[^a-z]xie[^a-z] @=>亵" },
  { "rule": "[^a-z]yao[^a-z] @=>药" },
  { "rule": "[^a-z]yin[^a-z] @=>淫" },
  { "rule": "[^a-z]you[^a-z] @=>诱" },
  { "rule": "[^a-z]bo[^a-z] @=>波" },
  { "rule": "[^a-z]ji[^a-z] @=>饥" },
  { "rule": "[^a-z]ke[^a-z] @=>渴" },
  { "rule": "[^a-z]ku[^a-z] @=>裤" },
  { "rule": "[^a-z]lu[^a-z] @=>露" },
  { "rule": "[^a-z]mi[^a-z] @=>迷" },
  { "rule": "[^a-z]mo[^a-z] @=>摸" },
  { "rule": "[^a-z]nv[^a-z] @=>女" },
  { "rule": "[^a-z]ri[^a-z] @=>日" },
  { "rule": "[^a-z]se[^a-z] @=>色" },
  { "rule": "[^a-z]si[^a-z] @=>私" },
  { "rule": "[^a-z]wu[^a-z] @=>抚" },
  { "rule": "[^a-z]xi[^a-z] @=>习" },
  { "rule": "[^a-z]yu[^a-z] @=>欲" },
  { "rule": "＂Ａ　ｐｉａｎ＂ @=>A片" },
  { "rule": "＂ａｉ　ｙｅ＂ @=>爱液" },
  { "rule": "＂ｂｉａｏ　ｚｉ＂ @=>婊子" },
  { "rule": "＂ｂｏ　ｂｏ＂ @=>波波" },
  { "rule": "＂ｃｉ　ｌｕｏ＂ @=>赤裸" },
  { "rule": "＂ｃｈｉ　ｌｕｏ＂ @=>赤裸" },
  { "rule": "＂ｄａｎｇ　ｆｕ＂ @=>荡妇" },
  { "rule": "＂ｇａｏ　ｃｈａｏ＂ @=>高潮" },
  { "rule": "＂ｇａｎ　ｓｉ　ｎｉ＂ @=>干死你" },
  { "rule": "＂ｊｉ　ｎｖ＂ @=>妓女" },
  { "rule": "＂ｊｉａｏ　ｃｈｕａｎ＂ @=>娇喘" },
  { "rule": "＂ｊｉａｎ　ｓｈｉ＂ @=>奸尸" },
  { "rule": "＂ｊｉａｎ　ｙｉｎ＂ @=>奸淫" },
  { "rule": "＂ｊｉｎｇ　ｙｅ＂ @=>精液" },
  { "rule": "＂ｊｕ　ｒｕ＂ @=>巨乳" },
  { "rule": "＂ｋａｉ　ｂａｏ＂ @=>开苞" },
  { "rule": "＂ｋｏｕ　ｈｕｏ＂ @=>口活" },
  { "rule": "＂ｋｏｕ　ｊｉａｏ＂ @=>口交" },
  { "rule": "＂ｌｕａｎ　ｌｕｎ＂ @=>乱伦" },
  { "rule": "＂ｌｕｏ　ｎｖ＂ @=>裸女" },
  { "rule": "＂ｍａｏ　ｚｅ　ｄｏｎｇ＂ @=>毛泽东" },
  { "rule": "＂ｍｉ　ｊｉａｎ＂ @=>迷奸" },
  { "rule": "＂ｍｉ　ｙａｏ＂ @=>迷药" },
  { "rule": "＂ｎｖ　ｙｏｕ＂ @=>女友" },
  { "rule": "＂ｐｉ　ｙａｎ＂ @=>屁眼" },
  { "rule": "＂ｐｏ　ｃｈｕ＂ @=>破处" },
  { "rule": "＂ｑｉ　ｑｕｎｅｉ　ｙｉ＂ @=>情趣内衣" },
  { "rule": "＂ｑｉａｎｇ　ｊｉａｎ＂ @=>强奸" },
  { "rule": "＂ｑｉａｏ　ｔｕｎ＂ @=>翘臀" },
  { "rule": "＂ｑｉｎｇ　ｒｅｎ＂ @=>情人" },
  { "rule": "＂ｒｏｕ　ｂａｎｇ＂ @=>肉棒" },
  { "rule": "＂ｒｕ　ｔｏｕ＂ @=>乳头" },
  { "rule": "＂ｒｕ　ｆａｎｇ＂ @=>乳房" },
  { "rule": "＂ｓａｏ　ｈｕｏ＂ @=>骚货" },
  { "rule": "＂ｓｅ　ｑｉｎ＂ @=>色情" },
  { "rule": "＂ｓｅ　ｔｕ＂ @=>色图" },
  { "rule": "＂ｓｅ　ｙｕ＂ @=>色欲" },
  { "rule": "＂ｓｈｅ　ｊｉｎ＂ @=>射精" },
  { "rule": "＂ｓｈｅｎ　ｙｉｎ＂ @=>呻吟" },
  { "rule": "＂ｓｈｅｎｇ　ｚｈｉ　ｑｉ＂ @=>生殖器" },
  { "rule": "＂ｓｈｏｕ　ｊｉａｏ＂ @=>兽交" },
  { "rule": "＂ｓｈｕ　ｘｉｏｎｇ＂ @=>酥胸" },
  { "rule": "＂ｓｈｕａｎｇ　ｆｅｎｇ＂ @=>双峰" },
  { "rule": "＂ｓｈｕａｎｇ　ｒｕ＂ @=>双乳" },
  { "rule": "＂ｔａｉ　ｄｕ＂ @=>台独" },
  { "rule": "＂ｘｉ　ｙｕ＂ @=>性欲" },
  { "rule": "＂ｘｉ　ｎｕ＂ @=>性奴" },
  { "rule": "＂ｘｉａｏ　ｊｉ　ｊｉ＂ @=>小鸡鸡" },
  { "rule": "＂ｘｉｏｎｇ　ｚａｏ＂ @=>胸罩" },
  { "rule": "＂ｙａｎｇ　ｊｕ＂ @=>阳具" },
  { "rule": "＂ｙｉ　ｙｅ　ｑｉｎｇ＂ @=>一夜情" },
  { "rule": "＂ｙｉｎ　ｄａｏ＂ @=>阴道" },
  { "rule": "＂ｙｉｎ　ｙｕ＂ @=>淫欲" },
  { "rule": "＂ｙｕｎ　ｘｉ＂ @=>吮吸" },
  { "rule": "＂ｚｉ　ｗｅｉ＂ @=>自慰" },
  { "rule": "＂ｚｈａｏ　ｊｉ＂ @=>召妓" },
  { "rule": "b长 @=>部长" },
  { "rule": "c(?=[经政]) @=>财" },
  { "rule": "g业 @=>工业" },
  { "rule": "g产 @=>共产" },
  { "rule": "g命 @=>革命" },
  { "rule": "j(?=[委方队]) @=>军" },
  { "rule": "x传 @=>宣传" },
  { "rule": "z[y央] @=>中央" },
  { "rule": "z委 @=>政委" },
  { "rule": "zzj @=>政治局" },
  { "rule": "zz @=>政治" },
  { "rule": "政zhi @=>政治" },
  { "rule": "大6(?={^0-9}) @=>大陆" },
  { "rule": "(?<=[^0-9])6(?=[地离续]) @=>陆" },
  { "rule": "仈jiǔ @=>八九" },
  { "rule": "鸡女 @=>妓女" },
  { "rule": "政洽 @=>政治" },
  { "rule": "白勺 @=>的" },
  { "rule": "口亨 @=>哼" },
  { "rule": "读力 @=>独立" },
  { "rule": "[oO0口]阿 @=>啊" },
  { "rule": "艹 @=>操" },
  { "rule": "ォ @=>才" },
  { "rule": "夕(?=[法客意招尖芒而归势气归骑士]) @=>剑" },
  { "rule": "(?<=[^夭])夭(?=[^夭折艳]) @=>天" },
  { "rule": "(?=十[有之])\\*\\* @=>八九" },
  { "rule": "\\*\\*(?=(玄功|不离十)) @=>八九" },
  { "rule": "波ss @=>BOSS" },
  { "rule": "迷ss @=>miss" },
  { "rule": "uu @=>00" },
  { "rule": "系～～*统 @=>系统" },
  { "rule": "(?<=[微腾新])[＂＝](?=[信讯浪]) @=>" },
  { "rule": "\\*\\*(?=[岁点个万岁米点个十百千万秒分月天年人]) @=>八九" },
  { "rule": "\\*\\*(?=[师则官残]) @=>大法" },
  { "rule": "(?<=[体水回顶])\\*\\* @=>大法" },
  { "rule": "\\*\\*(?=[融力][合量]) @=>肉体" },
  { "rule": "\\*\\*(?=[部区装队方务需人]) @=>国军" },
  { "rule": "(?<=[^马])厩 @=>北京" },
  { "rule": "洞\\* @=>洞穴" },
  { "rule": "走\\* @=>走光" },
  { "rule": "\\*光 @=>春光" },
  { "rule": "\\*\\*(?=[作劳纵控]) @=>操" },
  { "rule": "\\*\\*道 @=>不厚道" },
  { "rule": "\\*\\*丝 @=>屌丝" },
  { "rule": "\\*\\*大革命 @=>文化大革命" },
  { "rule": "感\\*\\*彩 @=>感情色彩" },
  { "rule": "八荒\\*\\* @=>八荒六合" },
  { "rule": "\\*\\*彩 @=>六合彩" },
  { "rule": "\\*\\*烦 @=>大麻烦" },
  { "rule": "余\\*\\*及 @=>余波波及" },
  { "rule": "轩然大\\* @=>轩然大波" },
  { "rule": "(?<=(玩家|个人)\\*\\* @=>玩家隐私" },
  { "rule": "赤身\\*\\* @=>赤身裸体" },
  { "rule": "\\*\\*(?=[件故]) @=>性事" },
  { "rule": "(?<=[爹妈妈姑姨])\\*\\* @=>妈的" },
  { "rule": "\\*\\*裸 @=>赤裸裸" },
  { "rule": "一\\*\\* @=>一波波" },
  { "rule": "他\\*\\* @=>他妈" },
  { "rule": "天灾\\*\\* @=>天灾人祸" },
  { "rule": "寻求\\*\\* @=>寻求真理" },
  { "rule": "\\*级 @=>A级" },
  { "rule": "\\*子 @=>婊子" },
  { "rule": "[‘“] @=>「" },
  { "rule": "[’”] @=>」" },
  { "rule": "^」 @=>「" },
  { "rule": "「$ @=>」" },
  { "rule": "　* @=>" },
  { "rule": "~ @=>～" },
  { "rule": "&#[0-9]{2,5}; @=>" },
  { "rule": "&nbsp; @=>" },
  { "rule": "n*bsp; @=>" },
  { "rule": "&#160; @=>" },
  { "rule": "&amp; @=>&" },
  { "rule": "&quot; @=>「" },
  { "rule": "&middot; @=>·" },
  { "rule": "&ldquo; @=>「" },
  { "rule": "&rdquo; @=>」" },
  { "rule": "&lt; @=><" },
  { "rule": "&gt; @=>>" },
  { "rule": "<a href=.*<\\ @=>a>" },
  { "rule": "^\\s* @=>" },
  { "rule": "<![^>]*> @=>" },
  { "rule": "[\\{｛][^}]*} @=>" },
  { "rule": "纯文字在线阅读 @=>" },
  { "rule": "本站域名 @=>" },
  { "rule": "手机同步阅读请访问 @=>" },
  { "rule": "提供最快最新的小说 @=>" },
  { "rule": "书海阁 @=>" },
  { "rule": "搜索最新更新尽在.*$ @=>" },
  { "rule": "\\(小说.*$ @=>" },
  { "rule": "本文由[^首]*首发 @=>" },
  { "rule": "[(（]本章免费[)）] @=>" },
  { "rule": "[(（]*未完待续.*$ @=>" },
  { "rule": "[(（]*作品未完.*$ @=>" },
  { "rule": "看小说就到.*$ @=>" },
  { "rule": "起点中文网.*$ @=>" },
  { "rule": "飘天文学网 @=>" },
  { "rule": "无错小说网不[少跳]字 @=>" },
  { "rule": "最新最快章节.*$ @=>" },
  { "rule": "更多全本.*$ @=>" },
  { "rule": "欢迎广大书友光临.*$ @=>" },
  { "rule": "免费电子书下载 @=>" },
  { "rule": "78xs @=>" },
  { "rule": "[wWBOKbok\\s]{1,4}\\.[a-zA-Z0-9\\s]*\\.[comCOMnetNET\\s]{1,4} @=>" },
  { "rule": "8.9.阅.读.网 @=>" },
  { "rule": "[☆]*新.思.路.中.文.网.*[☆]* @=>" },
  { "rule": "无.弹.窗.小.说.网 @=>" },
  { "rule": "无弹窗 @=>" },
  { "rule": "[(（]河蟹[)）] @=>" },
  { "rule": "r[0-9]+$ @=>" },
  { "rule": "\\[\\.] @=>" },
  { "rule": "[【】〖〗『』＊◆●★垩齤囘冇龘悳圌] @=>" },
  { "rule": "[《「{（(][《「{(。\\.~ ]*[)」}》][)）}」》]* @=>" },
  { "rule": "^[)）、，。？！＂：;,\\-\\*]* @=>" },
  { "rule": "(?<=[。」？！）])[\\(\\)（）\\[《、，。？！：＂…,—\\-]*$ @=>" },
  { "rule": "(?<=[a-zA-Z])「(?=[a-zA-Z]) @=>'" },
  { "rule": "[-－—※]{2,} @=>——" }
]
